{
  "format_version": "1.10.0",
  "minecraft:client_entity": {
    "description": {
      "identifier": "abyss:nest",
      "materials": {
        "default": "abyss"
      },
      "textures": {
        "default": "textures/entity/boss/Dread_guard"
      },
      "geometry": {
        "default": "geometry.nest"
      },
      "animations": {
        "move": "animation.nest.move",    
        "look_at_target": "animation.common.look_at_target"
      },
      "animation_controllers": [
        { "move": "controller.animation.nest.move" }
      ],
      "scripts": {
        "animate": [
          "move"
        ]  
      },
      "render_controllers": [ "controller.render.nest" ],
       "spawn_egg": {
        "overlay_color": "#2202060",
        "base_color": "#13900"
      }
    }
  }
}